splatplost/__init__.py
splatplost/generate_route.py
splatplost/plot.py
splatplost/tsp_solver_dp.py
splatplost-0.1.4.data/scripts/splatplan
splatplost-0.1.4.data/scripts/splatplot
splatplost-0.1.4.dist-info/LICENSE
splatplost-0.1.4.dist-info/METADATA
splatplost-0.1.4.dist-info/WHEEL
splatplost-0.1.4.dist-info/top_level.txt
splatplost-0.1.4.dist-info/RECORD
