Metadata-Version: 2.1
Name: splatplost
Version: 0.1.4
Summary: A software-based SplatPost plotter.
Home-page: https://github.com/Victrid/splatplost
Author: Weihao Jiang
Author-email: weihau.chiang@gmail.com
License: GPLv3
Classifier: Development Status :: 3 - Alpha
License-File: LICENSE
Requires-Dist: numpy (~=1.23.2)
Requires-Dist: Pillow (~=9.2.0)
Requires-Dist: setuptools (~=65.3.0)
Requires-Dist: scipy (~=1.9.1)
Requires-Dist: tqdm (~=4.64.0)
Requires-Dist: scikit-image (~=0.19.3)
Requires-Dist: libnxctrl (~=0.1.7)
Requires-Dist: tsp-solver2 (~=0.4.1)
